{"contracts":[{"childhome":"/smart_contracts","from":"none","gas":"none","home":"/home/liuye","name":"CentrallyIssuedToken","param_Names":["_owner","_name","_symbol","_totalSupply","_decimals"],"param_Types":["address","string","string","uint256","uint256"],"param_Values":{"_decimals":7,"_name":"Gucci Gang Coin","_owner":"0xf2e6b44e0ffd524bd36cae1a58d9f6ee2edffb1e","_symbol":"GGC","_totalSupply":100000000},"payable":false,"value":"none","values":["0xf2e6b44e0ffd524bd36cae1a58d9f6ee2edffb1e","Gucci Gang Coin","GGC",100000000,7]}],"from":"none","gas":"50000000000","home":"/home/liuye","value":"1000000000"}